clockman/__init__.py
clockman/cli/__init__.py
clockman/cli/main.py
clockman/core/__init__.py
clockman/core/time_tracker.py
clockman/db/__init__.py
clockman/db/models.py
clockman/db/repository.py
clockman/db/schema.py
clockman/tests/__init__.py
clockman/tests/conftest.py
clockman/tests/test_cli_main.py
clockman/tests/test_config.py
clockman/tests/test_formatting.py
clockman/tests/test_models.py
clockman/tests/test_notification.py
clockman/tests/test_repository.py
clockman/tests/test_schema.py
clockman/tests/test_time_tracker.py
clockman/utils/__init__.py
clockman/utils/config.py
clockman/utils/formatting.py
clockman/utils/notifier.py
clockman-1.0.0.dist-info/METADATA
clockman-1.0.0.dist-info/WHEEL
clockman-1.0.0.dist-info/entry_points.txt
clockman-1.0.0.dist-info/licenses/LICENSE
clockman-1.0.0.dist-info/RECORD
