Metadata-Version: 2.4
Name: clockman
Version: 1.0.0
Summary: Terminal-based time tracking for developers
Project-URL: Homepage, https://github.com/theany-org/clockman
Project-URL: Repository, https://github.com/theany-org/clockman.git
Project-URL: Issues, https://github.com/theany-org/clockman/issues
Author-email: Theany Team <epicrr001@gmail.com>
License: MIT
License-File: LICENSE
Keywords: cli,productivity,terminal,time-tracking
Classifier: Development Status :: 3 - Alpha
Classifier: Environment :: Console
Classifier: Intended Audience :: Developers
Classifier: License :: OSI Approved :: MIT License
Classifier: Operating System :: OS Independent
Classifier: Programming Language :: Python :: 3
Classifier: Programming Language :: Python :: 3.11
Classifier: Programming Language :: Python :: 3.12
Classifier: Topic :: Office/Business
Classifier: Topic :: Utilities
Requires-Python: >=3.11
Requires-Dist: desktop-notifier>=6.0.0
Requires-Dist: platformdirs>=4.0.0
Requires-Dist: pydantic>=2.5.0
Requires-Dist: rich>=13.0.0
Requires-Dist: typer>=0.9.0
Provides-Extra: dev
Requires-Dist: black>=23.0.0; extra == 'dev'
Requires-Dist: flake8>=6.0.0; extra == 'dev'
Requires-Dist: isort>=5.12.0; extra == 'dev'
Requires-Dist: mypy>=1.5.0; extra == 'dev'
Requires-Dist: pre-commit>=3.4.0; extra == 'dev'
Requires-Dist: pytest-asyncio>=0.25.0; extra == 'dev'
Requires-Dist: pytest-cov>=4.1.0; extra == 'dev'
Requires-Dist: pytest-mock>=3.11.0; extra == 'dev'
Requires-Dist: pytest>=7.4.0; extra == 'dev'
